{
    "remarks": "123456asdfasdf",
    "sourceOrderType": "PO",
    "id": "4596014558940942340",
    "referenceOrders": [
        {
            "referenceOrderNo": "PO20210117",
            "referenceOrderType": "FLT_PUR"
        }
    ],
    "shippingInfo": {
        "partialShipmentAllowed": true,
        "selfProvidedCabinet": true,
        "transhipmentAllowed": true,
        "seaTransportationNode": {
            "designatedSeaport": true,
            "originSeaportId": "CNYTG",
            "dischargeSeaportId": "CNDYN"
        },
        "reqTimeOfDepart": 1622776198000,
        "reqTimeOfArrival ": 1622862598000,
        "etd": 1657784368000,
        "eta": 1689320368000,
        "loadingTypeCode": "CTM_LCL",
        "serviceModeCode": "SEL_D2Y",
        "incotermsCode": "INT_FAS",
        "billOfLadingTypeCode": "LBT_OBR",
        "containerInfos": [
            {
                "containerSizeCode": "CTT_40FROWOH",
                "containerSizeName": "20FROWOH",
                "containerType": "BU",
                "containerTypeCode": "ICT_BU",
                "requestContainerQty": 12
            }
        ],
        "originCityId": "SCI105647",
        "originLocationCode": "CNSZZ",
        "destinationCityId": "SCI106141",
        "destinationLocationCode": "USLAX",
        "shipper": {
            "contactPartnerId": "4596013356350074880",
            "contactPartnerName": "Appraisal Clips Erasers GmbH",
            "contactPartnerType": "SHIPPER",
            "addressAbbreviation": "CHINA",
            "addressCode": "GUANGDONG PROVINCE",
            "countryCode": "CN",
            "countryName": "CHINA",
            "provinceCode": "CN-44",
            "provinceName": "GUANGDONG PROVINCE",
            "cityCode": "SCI105647",
            "cityName": "SHENZHEN",
            "districtCode": "SCT104592",
            "districtName": "YUHU",
            "streetCode": "SST217437",
            "streetName": "TAIPING TOWN",
            "addressDetail": "SHENZHEN",
            "postCode": "854352",
            "contactName": "messes",
            "telephoneArea": "967",
            "telephoneNumber": "854352",
            "mobileNumber": "19946731046",
            "mobileArea": "967",
            "email": "Hjx6zzDwT3@126.com",
            "transportLocationCode": "CNSZZ",
            "isDefault": true,
            "isInternationalPartner": true
        },
        "pickUp": true,
        "marksAndNumbers": "蒰婚",
        "shippingAddress": {
            "contactPartnerAddressId": "4596013364940009472",
            "addressAbbreviation": "CHINA",
            "addressCode": "GUANGDONG PROVINCE",
            "countryCode": "CN",
            "countryName": "CHINA",
            "provinceCode": "CN-44",
            "provinceName": "GUANGDONG PROVINCE",
            "cityCode": "SCI105647",
            "cityName": "SHENZHEN",
            "districtCode": "SCT104592",
            "districtName": "YUHU",
            "streetCode": "SST217437",
            "streetName": "TAIPING TOWN",
            "addressDetail": "SHENZHEN",
            "postCode": "83856",
            "contactName": "nines",
            "telephoneArea": "967",
            "telephoneNumber": "83856",
            "mobileNumber": "13358845662",
            "mobileArea": "967",
            "email": "LXJsQd5a2y@qq.com",
            "transportLocationCode": "CNSZZ",
            "isDefault": false,
            "isInternationalPartner": true
        },
        "consignee": {
            "contactPartnerId": "4596013373529944064",
            "contactPartnerName": "Needle Washes Terminator Corp.",
            "contactPartnerType": "CONSIGNEE",
            "addressAbbreviation": "UNITED STATES OF AMERICA",
            "addressCode": "CALIFORNIA",
            "countryCode": "US",
            "countryName": "UNITED STATES OF AMERICA",
            "provinceCode": "US-CA",
            "provinceName": "CALIFORNIA",
            "cityCode": "SCI106141",
            "cityName": "LOS ANGELES",
            "districtCode": "SCT106194",
            "districtName": "BEIHAIJIE STREET",
            "streetCode": "SST220700",
            "streetName": "SANCHA TOWN",
            "addressDetail": "LOS ANGELES",
            "postCode": "442406",
            "contactName": "nulls",
            "telephoneArea": "967",
            "telephoneNumber": "442406",
            "mobileNumber": "15959002468",
            "mobileArea": "967",
            "email": "BVHHGMcyqf@qq.com",
            "transportLocationCode": "USLAX",
            "isDefault": true,
            "isInternationalPartner": true
        },
        "takeDelivery": true,
        "receivingAddress": {
            "contactPartnerAddressId": "4596013382119878656",
            "addressAbbreviation": "UNITED STATES OF AMERICA",
            "addressCode": "CALIFORNIA",
            "countryCode": "US",
            "countryName": "UNITED STATES OF AMERICA",
            "provinceCode": "US-CA",
            "provinceName": "CALIFORNIA",
            "cityCode": "SCI106141",
            "cityName": "LOS ANGELES",
            "districtCode": "SCT106194",
            "districtName": "BEIHAIJIE STREET",
            "streetCode": "SST220700",
            "streetName": "SANCHA TOWN",
            "addressDetail": "LOS ANGELES",
            "postCode": "77266",
            "contactName": "washers",
            "telephoneArea": "967",
            "telephoneNumber": "77266",
            "mobileNumber": "15171896610",
            "mobileArea": "967",
            "email": "7CqGVoxlxw@126.com",
            "transportLocationCode": "USLAX",
            "isDefault": false,
            "isInternationalPartner": true
        },
        "notifyParty": {
            "contactPartnerId": "4596013390709813248",
            "contactPartnerName": "Exteriors Absence Guideline OY",
            "contactPartnerType": "NOTIFY_PARTY",
            "addressAbbreviation": "UNITED STATES OF AMERICA",
            "addressCode": "GUANGDONG PROVINCE",
            "countryCode": "US",
            "countryName": "UNITED STATES OF AMERICA",
            "provinceCode": "US-CA",
            "provinceName": "CALIFORNIA",
            "cityCode": "SCI106141",
            "cityName": "LOS ANGELES",
            "districtCode": "SCT104592",
            "districtName": "YUHU",
            "streetCode": "SST217437",
            "streetName": "TAIPING TOWN",
            "addressDetail": "LOS ANGELES",
            "postCode": "32202",
            "contactName": "hazards",
            "telephoneArea": "967",
            "telephoneNumber": "32202",
            "mobileNumber": "13997320139",
            "mobileArea": "967",
            "email": "p0I911HG6V@163.com",
            "transportLocationCode": "CNSZZ",
            "isDefault": true,
            "isInternationalPartner": true
        },
        "entrustedParty": {
            "contactPartnerId": "4596013399299747840",
            "contactPartnerName": "Explosions Toes Pond AB",
            "contactPartnerType": "CONSIGNOR",
            "addressAbbreviation": "CHINA",
            "addressCode": "CALIFORNIA",
            "countryCode": "CN",
            "countryName": "CHINA",
            "provinceCode": "CN-44",
            "provinceName": "GUANGDONG PROVINCE",
            "cityCode": "SCI105647",
            "cityName": "SHENZHEN",
            "districtCode": "SCT106194",
            "districtName": "BEIHAIJIE STREET",
            "streetCode": "SST220700",
            "streetName": "SANCHA TOWN",
            "addressDetail": "SHENZHEN",
            "postCode": "624981",
            "contactName": "nose",
            "telephoneArea": "967",
            "telephoneNumber": "624981",
            "mobileNumber": "13428057141",
            "mobileArea": "967",
            "email": "KS9bawERmU@163.com",
            "transportLocationCode": "USLAX",
            "isDefault": true,
            "isInternationalPartner": true
        }
    },
    "cargoInfo": {
        "dangerousCargo": true,
        "cargoTypeCode": "CAT_DGG",
        "grossWeight": 12.86,
        "grossWeightUnitCode": "KG",
        "pieceQty": 11,
        "pieceQtyUnitCode": "PUT_PAI",
        "totalPackageQty": 12,
        "totalPackageQtyUnitCode": "PUT_PAI",
        "totalVolume": 13,
        "totalVolumeUnitCode": "M3",
        "bulkCartonQty": 14,
        "bulkCartonQtyUnitCode": "PUT_PAI",
        "cargoDescription": "1231456asdfasdfasdkfj!",
        "cargoInfoLines": [
            {
                "companyPn": "PN20201219",
                "descriptionGoods": "HWDbf8QvI4",
                "hsCode": "HWDbf8QvI4",
                "invoiceNumber": "HWDbf8QvI4",
                "packageQuantity": 1,
                "packageUnitCode": "PUT_MIX",
                "referenceLineNo": "1",
                "referenceNo": "PO20210117",
                "unitPrice": "1.000011",
                "volume": "1.000011",
                "width": "1.000011",
                "amount": "1.000011",
                "height": "1.000011",
                "length": "1.000011",
                "currencyCode": "NOK",
                "grossWeight": "33.000011",
                "netWeight": "30.000011"
            }
        ]
    },
    "valueAddedBusiness": {
        "cargoValue": 10,
        "currencyCode": "NOK",
        "insurance": true,
        "entrustCustomsDeclaration": false,
        "customsBroker": "691736",
        "insuredValue": 11
    },
    "attachments": [
        {
            "name": "FLT_IVO_2020-12-24__13_38_59.xlsx",
            "typeCode": "FLT_IVO",
            "url": 1862832
        },
        {
            "name": "FLT_PAL_2020-12-24__13_38_59.xlsx",
            "typeCode": "FLT_PAL",
            "url": 1862833
        },
        {
            "name": "FLT_DAO_2020-12-24__13_39_00.xlsx",
            "typeCode": "FLT_DAO",
            "url": 1862834
        },
        {
            "name": "FLT_MBL_2020-12-24__13_39_01.xlsx",
            "typeCode": "FLT_MBL",
            "url": 1862835
        },
        {
            "name": "FLT_HBL_2020-12-24__13_39_01.xlsx",
            "typeCode": "FLT_HBL",
            "url": 1862836
        },
        {
            "name": "FLT_PODF_2020-12-24__13_39_02.xlsx",
            "typeCode": "FLT_PODF",
            "url": 1862837
        },
        {
            "name": "FLT_BKG_2020-12-24__13_39_02.xlsx",
            "typeCode": "FLT_BKG",
            "url": 1862838
        },
        {
            "name": "FLT_AGI_2020-12-24__13_39_03.xlsx",
            "typeCode": "FLT_AGI",
            "url": 1862839
        },
        {
            "name": "FLT_ARC_2020-12-24__13_39_03.xlsx",
            "typeCode": "FLT_ARC",
            "url": 1862840
        },
        {
            "name": "FLT_ARN_2020-12-24__13_39_04.xlsx",
            "typeCode": "FLT_ARN",
            "url": 1862841
        },
        {
            "name": "FLT_BCA_2020-12-24__13_39_04.xlsx",
            "typeCode": "FLT_BCA",
            "url": 1862842
        },
        {
            "name": "FLT_BOE_2020-12-24__13_39_05.xlsx",
            "typeCode": "FLT_BOE",
            "url": 1862843
        },
        {
            "name": "FLT_CTR_2020-12-24__13_39_05.xlsx",
            "typeCode": "FLT_CTR",
            "url": 1862844
        },
        {
            "name": "FLT_CUS_2020-12-24__13_39_06.xlsx",
            "typeCode": "FLT_CUS",
            "url": 1862845
        },
        {
            "name": "FLT_DAL_2020-12-24__13_39_07.xlsx",
            "typeCode": "FLT_DAL",
            "url": 1862846
        },
        {
            "name": "FLT_DAN_2020-12-24__13_39_07.xlsx",
            "typeCode": "FLT_DAN",
            "url": 1862847
        },
        {
            "name": "FLT_DEC_2020-12-24__13_39_08.xlsx",
            "typeCode": "FLT_DEC",
            "url": 1862848
        },
        {
            "name": "FLT_DGF_2020-12-24__13_39_08.xlsx",
            "typeCode": "FLT_DGF",
            "url": 1862849
        },
        {
            "name": "FLT_DNO_2020-12-24__13_39_09.xlsx",
            "typeCode": "FLT_DNO",
            "url": 1862850
        },
        {
            "name": "FLT_DRC_2020-12-24__13_39_10.xlsx",
            "typeCode": "FLT_DRC",
            "url": 1862851
        },
        {
            "name": "FLT_ECA_2020-12-24__13_39_10.xlsx",
            "typeCode": "FLT_ECA",
            "url": 1862852
        },
        {
            "name": "FLT_EXD_2020-12-24__13_39_10.xlsx",
            "typeCode": "FLT_EXD",
            "url": 1862853
        },
        {
            "name": "FLT_FUM_2020-12-24__13_39_11.xlsx",
            "typeCode": "FLT_FUM",
            "url": 1862854
        },
        {
            "name": "FLT_FWI_2020-12-24__13_39_12.xlsx",
            "typeCode": "FLT_FWI",
            "url": 1862855
        },
        {
            "name": "FLT_GTP_2020-12-24__13_39_12.xlsx",
            "typeCode": "FLT_GTP",
            "url": 1862856
        },
        {
            "name": "FLT_ICA_2020-12-24__13_39_13.xlsx",
            "typeCode": "FLT_ICA",
            "url": 1862857
        },
        {
            "name": "FLT_INB_2020-12-24__13_39_13.xlsx",
            "typeCode": "FLT_INB",
            "url": 1862858
        },
        {
            "name": "FLT_IRT_2020-12-24__13_39_14.xlsx",
            "typeCode": "FLT_IRT",
            "url": 1862859
        },
        {
            "name": "FLT_LID_2020-12-24__13_39_14.xlsx",
            "typeCode": "FLT_LID",
            "url": 1862860
        },
        {
            "name": "FLT_MAN_2020-12-24__13_39_15.xlsx",
            "typeCode": "FLT_MAN",
            "url": 1862861
        },
        {
            "name": "FLT_MCD_2020-12-24__13_39_15.xlsx",
            "typeCode": "FLT_MCD",
            "url": 1862862
        },
        {
            "name": "FLT_BKC_2020-12-24__13_39_16.xlsx",
            "typeCode": "FLT_BKC",
            "url": 1862863
        },
        {
            "name": "FLT_ISF_2020-12-24__13_39_16.xlsx",
            "typeCode": "FLT_ISF",
            "url": 1862864
        },
        {
            "name": "FLT_SLI_2020-12-24__13_39_17.xlsx",
            "typeCode": "FLT_SLI",
            "url": 1862865
        },
        {
            "name": "FLT_PALT_2020-12-24__13_39_18.xlsx",
            "typeCode": "FLT_PALT",
            "url": 1862866
        },
        {
            "name": "FLT_AIN_2020-12-24__13_39_18.xlsx",
            "typeCode": "FLT_AIN",
            "url": 1862867
        },
        {
            "name": "FLT_ICRA_2020-12-24__13_39_19.xlsx",
            "typeCode": "FLT_ICRA",
            "url": 1862868
        },
        {
            "name": "FLT_BOL_2020-12-24__13_39_19.xlsx",
            "typeCode": "FLT_BOL",
            "url": 1862869
        },
        {
            "name": "FLT_CAD_2020-12-24__13_39_20.xlsx",
            "typeCode": "FLT_CAD",
            "url": 1862870
        },
        {
            "name": "FLT_CAU_2020-12-24__13_39_21.xlsx",
            "typeCode": "FLT_CAU",
            "url": 1862871
        },
        {
            "name": "FLT_CDR_2020-12-24__13_39_21.xlsx",
            "typeCode": "FLT_CDR",
            "url": 1862872
        },
        {
            "name": "FLT_CIV_2020-12-24__13_39_22.xlsx",
            "typeCode": "FLT_CIV",
            "url": 1862873
        },
        {
            "name": "FLT_COR_2020-12-24__13_39_22.xlsx",
            "typeCode": "FLT_COR",
            "url": 1862874
        },
        {
            "name": "FLT_COF_2020-12-24__13_39_23.xlsx",
            "typeCode": "FLT_COF",
            "url": 1862875
        },
        {
            "name": "FLT_COU_2020-12-24__13_39_23.xlsx",
            "typeCode": "FLT_COU",
            "url": 1862876
        },
        {
            "name": "FLT_CST_2020-12-24__13_39_24.xlsx",
            "typeCode": "FLT_CST",
            "url": 1862877
        },
        {
            "name": "FLT_MCF_2020-12-24__13_39_24.xlsx",
            "typeCode": "FLT_MCF",
            "url": 1862878
        },
        {
            "name": "FLT_MDC_2020-12-24__13_39_25.xlsx",
            "typeCode": "FLT_MDC",
            "url": 1862879
        },
        {
            "name": "FLT_NOT_2020-12-24__13_39_25.xlsx",
            "typeCode": "FLT_NOT",
            "url": 1862880
        },
        {
            "name": "FLT_OBL_2020-12-24__13_39_26.xlsx",
            "typeCode": "FLT_OBL",
            "url": 1862881
        },
        {
            "name": "FLT_SDN_2020-12-24__13_39_26.xlsx",
            "typeCode": "FLT_SDN",
            "url": 1862882
        },
        {
            "name": "FLT_SDS_2020-12-24__13_39_27.xlsx",
            "typeCode": "FLT_SDS",
            "url": 1862883
        },
        {
            "name": "FLT_TSC_2020-12-24__13_39_27.xlsx",
            "typeCode": "FLT_TSC",
            "url": 1862884
        }
    ]
}