{
    "referenceOrders": [
        {
            "referenceOrderNo": "13163959838",
            "referenceOrderType": "FLT_REM"
        }
    ],
    "attachments": [
        {
            "name": "FLT_ABN_2020-10-28__11_53_06.xlsx",
            "typeCode": "FLT_ABN",
            "url": 42039
        },
        {
            "name": "FLT_ACT_2020-10-28__11_53_07.xlsx",
            "typeCode": "FLT_ACT",
            "url": 42040
        },
        {
            "name": "FLT_ECT_2020-10-28__11_53_07.xlsx",
            "typeCode": "FLT_ECT",
            "url": 42041
        },
        {
            "name": "FLT_EDF_2020-10-28__11_53_08.xlsx",
            "typeCode": "FLT_EDF",
            "url": 42042
        },
        {
            "name": "FLT_EMF_2020-10-28__11_53_08.xlsx",
            "typeCode": "FLT_EMF",
            "url": 42043
        },
        {
            "name": "FLT_EMR_2020-10-28__11_53_09.xlsx",
            "typeCode": "FLT_EMR",
            "url": 42044
        },
        {
            "name": "FLT_EPM_2020-10-28__11_53_09.xlsx",
            "typeCode": "FLT_EPM",
            "url": 42045
        },
        {
            "name": "FLT_FAP_2020-10-28__11_53_10.xlsx",
            "typeCode": "FLT_FAP",
            "url": 42046
        },
        {
            "name": "FLT_GMF_2020-10-28__11_53_10.xlsx",
            "typeCode": "FLT_GMF",
            "url": 42047
        },
        {
            "name": "FLT_AFD_2020-10-28__11_53_10.xlsx",
            "typeCode": "FLT_AFD",
            "url": 42048
        },
        {
            "name": "FLT_AIV_2020-10-28__11_53_11.xlsx",
            "typeCode": "FLT_AIV",
            "url": 42049
        },
        {
            "name": "FLT_APA_2020-10-28__11_53_11.xlsx",
            "typeCode": "FLT_APA",
            "url": 42050
        },
        {
            "name": "FLT_APF_2020-10-28__11_53_12.xlsx",
            "typeCode": "FLT_APF",
            "url": 42051
        },
        {
            "name": "FLT_APP_2020-10-28__11_53_13.xlsx",
            "typeCode": "FLT_APP",
            "url": 42052
        },
        {
            "name": "FLT_ATT_2020-10-28__11_53_13.xlsx",
            "typeCode": "FLT_ATT",
            "url": 42053
        },
        {
            "name": "FLT_CTF_2020-10-28__11_53_14.xlsx",
            "typeCode": "FLT_CTF",
            "url": 42054
        },
        {
            "name": "FLT_DAO_2020-10-28__11_53_14.xlsx",
            "typeCode": "FLT_DAO",
            "url": 42055
        },
        {
            "name": "FLT_DSD_2020-10-28__11_53_15.xlsx",
            "typeCode": "FLT_DSD",
            "url": 42056
        },
        {
            "name": "FLT_ECR_2020-10-28__11_53_15.xlsx",
            "typeCode": "FLT_ECR",
            "url": 42057
        },
        {
            "name": "FLT_HAWB_2020-10-28__11_53_16.xlsx",
            "typeCode": "FLT_HAWB",
            "url": 42058
        },
        {
            "name": "FLT_ICR_2020-10-28__11_53_16.xlsx",
            "typeCode": "FLT_ICR",
            "url": 42059
        },
        {
            "name": "FLT_IDF_2020-10-28__11_53_17.xlsx",
            "typeCode": "FLT_IDF",
            "url": 42060
        },
        {
            "name": "FLT_IMFW_2020-10-28__11_53_17.xlsx",
            "typeCode": "FLT_IMFW",
            "url": 42061
        },
        {
            "name": "FLT_IOM_2020-10-28__11_53_17.xlsx",
            "typeCode": "FLT_IOM",
            "url": 42062
        },
        {
            "name": "FLT_IVO_2020-10-28__11_53_18.xlsx",
            "typeCode": "FLT_IVO",
            "url": 42063
        },
        {
            "name": "FLT_PAL_2020-10-28__11_53_18.xlsx",
            "typeCode": "FLT_PAL",
            "url": 42064
        },
        {
            "name": "FLT_POD_2020-10-28__11_53_19.xlsx",
            "typeCode": "FLT_POD",
            "url": 42065
        },
        {
            "name": "FLT_RDD_2020-10-28__11_53_19.xlsx",
            "typeCode": "FLT_RDD",
            "url": 42066
        },
        {
            "name": "FLT_ROC_2020-10-28__11_53_20.xlsx",
            "typeCode": "FLT_ROC",
            "url": 42067
        },
        {
            "name": "FLT_SAO_2020-10-28__11_53_20.xlsx",
            "typeCode": "FLT_SAO",
            "url": 42068
        },
        {
            "name": "FLT_SPO_2020-10-28__11_53_21.xlsx",
            "typeCode": "FLT_SPO",
            "url": 42069
        }
    ],
    "shippingInfo": {
        "shipper": {
            "contactPartnerId": "4553652695208128512",
            "contactPartnerName": "保定搞怍测试集团有限公司",
            "contactPartnerType": "SHIPPER",
            "addressAbbreviation": "天津市",
            "addressCode": "蓟州区",
            "countryCode": "CN",
            "countryName": "China",
            "provinceCode": "CN-12",
            "provinceName": "Tianjin Municipality",
            "cityCode": "SCI105446",
            "cityName": "Tianjin",
            "districtCode": "SCT106654",
            "districtName": "Hongqiao",
            "streetCode": "SST217437",
            "streetName": "Taiping Town",
            "addressDetail": "公兴街道",
            "postCode": "610000",
            "contactName": "462837",
            "telephoneArea": "57",
            "telephoneNumber": "462837",
            "mobileNumber": "15778725506",
            "mobileArea": "0086",
            "email": "12123@qq.com",
            "isDefault": true,
            "isInternationalPartner": false
        },
        "shippingAddress": {
            "contactPartnerAddressId": "4553652695208128514",
            "addressAbbreviation": "天津市",
            "addressCode": "蓟州区",
            "countryCode": "CN",
            "countryName": "China",
            "provinceCode": "CN-12",
            "provinceName": "Tianjin Municipality",
            "cityCode": "SCI105446",
            "cityName": "Tianjin",
            "districtCode": "SCT106654",
            "districtName": "Hongqiao",
            "streetCode": "SST217437",
            "streetName": "Taiping Town",
            "addressDetail": "公兴街道",
            "postCode": "610000",
            "contactName": "279576",
            "telephoneArea": "57",
            "telephoneNumber": "15818622300",
            "mobileNumber": "279576",
            "mobileArea": "0086",
            "email": "12123@qq.com",
            "isDefault": false,
            "isInternationalPartner": false
        },
        "consignee": {
            "contactPartnerId": "4553652703798063104",
            "contactPartnerName": "齐齐哈尔箢筐物流集团",
            "contactPartnerType": "CONSIGNEE",
            "addressAbbreviation": "银川市",
            "addressCode": "惠农区",
            "countryCode": "CN",
            "countryName": "China",
            "provinceCode": "CN-64",
            "provinceName": "Ningxia Hui Autonomous Region",
            "cityCode": "SCI105787",
            "cityName": "Shizuishan",
            "districtCode": "SCT105692",
            "districtName": "Dawukou",
            "streetCode": "SST220707",
            "streetName": "Tashui Town",
            "addressDetail": "望水乡",
            "postCode": "610000",
            "contactName": "647548",
            "telephoneArea": "57",
            "telephoneNumber": "13346082196",
            "mobileNumber": "647548",
            "mobileArea": "0086",
            "email": "12123@qq.com",
            "isDefault": true,
            "isInternationalPartner": false
        },
        "receivingAddress": {
            "contactPartnerAddressId": "4553652703798063106",
            "addressAbbreviation": "银川市",
            "addressCode": "惠农区",
            "countryCode": "CN",
            "countryName": "China",
            "provinceCode": "CN-64",
            "provinceName": "Ningxia Hui Autonomous Region",
            "cityCode": "SCI105787",
            "cityName": "Shizuishan",
            "districtCode": "SCT105692",
            "districtName": "Dawukou",
            "streetCode": "SST220707",
            "streetName": "Tashui Town",
            "addressDetail": "望水乡",
            "postCode": "610000",
            "contactName": "903714",
            "telephoneArea": "57",
            "telephoneNumber": "13194632728",
            "mobileNumber": "903714",
            "mobileArea": "0086",
            "email": "12123@qq.com",
            "isDefault": false,
            "isInternationalPartner": false
        },
        "pickUp": true,
        "takeDelivery": true,
        "originCityId": "SCI437416",
        "destinationCityId": "SCI437440",
        "requiredPickupTime": 1622776198000,
        "requiredArrivalTime": 1622862598000,
        "serviceModeCode": "SEL_F2D",
        "paymentTypeCode": "PYT_PrePaid"
    },
    "cargoInfo": {
        "cargoTypeCode": "CAT_RWK",
        "grossWeight": 12.86,
        "grossWeightUnitCode": "KG",
        "pieceQty": 11,
        "pieceQtyUnitCode": "PUT_CARTON",
        "totalPackageQty": 12,
        "totalPackageQtyUnitCode": "PUT_CARTON",
        "totalVolume": 13,
        "totalVolumeUnitCode": "M3",
        "bulkCartonQty": 14,
        "bulkCartonQtyUnitCode": "PUT_CARTON",
        "cargoDescription": "1231456asdfasdfasdkfj!",
        "cargoInfoLines": [
            {
                "companyPn": "6SBnrWe0SP",
                "descriptionGoods": "6SBnrWe0SP",
                "hsCode": "6SBnrWe0SP",
                "invoiceNumber": "6SBnrWe0SP",
                "packageQuantity": 1200,
                "packageUnitCode": "PUT_PIECEJIAN",
                "referenceLineNo": "6SBnrWe0SP",
                "referenceNo": "6SBnrWe0SP",
                "unitPrice": "1877741",
                "volume": "2877741",
                "width": "8777413",
                "amount": "8777414",
                "height": "4877741",
                "length": "8777417",
                "currencyCode": "BRL",
                "grossWeight": "12345678.11",
                "netWeight": "12345.55"
            }
        ]
    },
    "valueAddedBusiness": {
        "cargoValue": 10.0,
        "currencyCode": "BRL",
        "insurance": true,
        "pod": true
    },
    "settlementInfo": {
        "consignorId": "4403721588833267713",
        "costCode": "10018181"
    }
}