{
    "referenceOrderGroups": {
        "FLT_PUR": {
            "referenceOrderTypeCode": "FLT_PUR",
            "referenceOrderNos": [
                "P7874655"
            ]
        }
    },
    "remarks": "15713046285",
    "sourceOrderType": "PO",
    "id": "4646580600489869312",
    "addressInfo": {
        "shippingAddress": {
            "contactPartnerId": "4646573144427388928",
            "contactPartnerAddressId": "4646573153017323520",
            "addressAbbreviation": "梅州市",
            "addressCode": "雷州市",
            "countryCode": "CN",
            "countryName": "CHINA",
            "provinceCode": "CN-44",
            "provinceName": "GUANGDONG PROVINCE",
            "cityCode": "SCI105652",
            "cityName": "ZHANJIANG",
            "districtCode": "SCT104756",
            "districtName": "LIANJIANG",
            "streetCode": "SST217431",
            "streetName": "XIHANGGANG STREET",
            "addressDetail": "永安镇",
            "postCode": "610000",
            "contactName": "288620",
            "telephoneArea": "375",
            "telephoneNumber": "15987006388",
            "mobileNumber": "288620",
            "mobileArea": "0086",
            "email": "12123@qq.com"
        },
        "receivingAddress": {
            "contactPartnerId": "4646573161607258112",
            "contactPartnerAddressId": "4646573170197192704",
            "addressAbbreviation": "衢州市",
            "addressCode": "江东区",
            "countryCode": "CN",
            "countryName": "CHINA",
            "provinceCode": "CN-33",
            "provinceName": "ZHEJIANG PROVINCE",
            "cityCode": "SCI105533",
            "cityName": "NINGBO",
            "districtCode": "SCT103821",
            "districtName": "YUYAO",
            "streetCode": "SST220733",
            "streetName": "LAOLONG TOWNSHIP",
            "addressDetail": "灵仙乡",
            "postCode": "610000",
            "contactName": "923415",
            "telephoneArea": "375",
            "telephoneNumber": "15568115350",
            "mobileNumber": "923415",
            "mobileArea": "0086",
            "email": "12123@qq.com"
        },
        "receivingAddressSameAsConsignee": true,
        "shippingAddressSameAsShipper": true,
        "originCityId": "SCI237814",
        "destinationCityId": "SCI237815"
    },
    "shippingInfo": {
        "shipper": {
            "contactPartnerId": "4646573144427388928",
            "contactPartnerName": "保定柝唔查单集团有限公司",
            "contactPartnerType": "SHIPPER",
            "addressAbbreviation": "梅州市",
            "addressCode": "雷州市",
            "countryCode": "CN",
            "countryName": "CHINA",
            "provinceCode": "CN-44",
            "provinceName": "GUANGDONG PROVINCE",
            "cityCode": "SCI105652",
            "cityName": "ZHANJIANG",
            "districtCode": "SCT104756",
            "districtName": "LIANJIANG",
            "streetCode": "SST217431",
            "streetName": "XIHANGGANG STREET",
            "addressDetail": "永安镇",
            "postCode": "610000",
            "contactName": "747276",
            "telephoneArea": "375",
            "telephoneNumber": "747276",
            "mobileNumber": "13045432017",
            "mobileArea": "0086",
            "email": "12123@qq.com",
            "isDefault": true,
            "isInternationalPartner": false
        },
        "consignee": {
            "contactPartnerId": "4646573161607258112",
            "contactPartnerName": "运城咳陉库存经营部",
            "contactPartnerType": "CONSIGNEE",
            "addressAbbreviation": "衢州市",
            "addressCode": "江东区",
            "countryCode": "CN",
            "countryName": "CHINA",
            "provinceCode": "CN-33",
            "provinceName": "ZHEJIANG PROVINCE",
            "cityCode": "SCI105533",
            "cityName": "NINGBO",
            "districtCode": "SCT103821",
            "districtName": "YUYAO",
            "streetCode": "SST220733",
            "streetName": "LAOLONG TOWNSHIP",
            "addressDetail": "灵仙乡",
            "postCode": "610000",
            "contactName": "147855",
            "telephoneArea": "375",
            "telephoneNumber": "18540214792",
            "mobileNumber": "147855",
            "mobileArea": "0086",
            "email": "12123@qq.com",
            "isDefault": true,
            "isInternationalPartner": false
        },
        "pickUp": true,
        "takeDelivery": true,
        "marksAndNumbers": "Grasses Glands Ventilation S.P.A.",
        "needMultiPickUpAndDelivery": false,
        "originCityId": "SCI237814",
        "destinationCityId": "SCI237815",
        "reqTimeOfDepart": 1622776198000,
        "reqTimeOfArrival ": 1622862598000,
        "serviceModeCode": "SEL_D2D",
        "paymentTypeCode": "PYT_PrePaid"
    },
    "cargoInfo": {
        "cargoTypeCode": "CAT_TSC",
        "grossWeight": 12.86,
        "grossWeightUnitCode": "KG",
        "pieceQty": 11,
        "pieceQtyUnitCode": "PUT_KEG",
        "totalPackageQty": 12,
        "totalPackageQtyUnitCode": "PUT_KEG",
        "totalVolume": 13,
        "totalVolumeUnitCode": "M3",
        "bulkCartonQty": 14,
        "bulkCartonQtyUnitCode": "PUT_KEG",
        "cargoDescription": "1231456asdfasdfasdkfj!",
        "cargoInfoLines": [
            {
                "companyPn": "12",
                "descriptionGoods": "12",
                "hsCode": "465ASDFASDF_A",
                "invoiceNumber": "ASDFaa",
                "referenceLineNo": "1",
                "referenceNo": "P7874655",
                "unitPrice": "13699.112233",
                "volume": "13699.112233",
                "width": "23699.112233",
                "amount": "33699.112233",
                "height": "43699.112233",
                "length": "53699.112233",
                "currencyCode": "RUB",
                "grossWeight": "83699.112233",
                "netWeight": "73699.112233",
                "bulkCartonQty": 1,
                "bulkCartonQtyUnitCode": "PUT_YARD",
                "originCityId": "SCI237814",
                "destinationCityId": "SCI237815",
                "pieceQty": 11,
                "pieceQtyUnitCode": "PUT_YARD",
                "cargoQty": 1,
                "cargoQtyUnitCode": "PUT_CARTON",
                "cartonNos": [
                    "15713046285"
                ],
                "totalPackageQty": 1,
                "totalPackageQtyUnitCode": "PUT_YARD",
                "referenceOrderGroups": {
                    "FLT_PUR": {
                        "referenceOrderTypeCode": "FLT_PUR",
                        "referenceOrderNos": [
                            "P7874655"
                        ]
                    }
                },
                "shippingAddress": {
                    "contactPartnerId": "4646573144427388928",
                    "contactPartnerAddressId": "4646573153017323520",
                    "addressAbbreviation": "梅州市",
                    "addressCode": "雷州市",
                    "countryCode": "CN",
                    "countryName": "CHINA",
                    "provinceCode": "CN-44",
                    "provinceName": "GUANGDONG PROVINCE",
                    "cityCode": "SCI105652",
                    "cityName": "ZHANJIANG",
                    "districtCode": "SCT104756",
                    "districtName": "LIANJIANG",
                    "streetCode": "SST217431",
                    "streetName": "XIHANGGANG STREET",
                    "addressDetail": "永安镇",
                    "postCode": "610000",
                    "contactName": "288620",
                    "telephoneArea": "375",
                    "telephoneNumber": "15987006388",
                    "mobileNumber": "288620",
                    "mobileArea": "0086",
                    "email": "12123@qq.com"
                },
                "receivingAddress": {
                    "contactPartnerId": "4646573161607258112",
                    "contactPartnerAddressId": "4646573170197192704",
                    "addressAbbreviation": "衢州市",
                    "addressCode": "江东区",
                    "countryCode": "CN",
                    "countryName": "CHINA",
                    "provinceCode": "CN-33",
                    "provinceName": "ZHEJIANG PROVINCE",
                    "cityCode": "SCI105533",
                    "cityName": "NINGBO",
                    "districtCode": "SCT103821",
                    "districtName": "YUYAO",
                    "streetCode": "SST220733",
                    "streetName": "LAOLONG TOWNSHIP",
                    "addressDetail": "灵仙乡",
                    "postCode": "610000",
                    "contactName": "923415",
                    "telephoneArea": "375",
                    "telephoneNumber": "15568115350",
                    "mobileNumber": "923415",
                    "mobileArea": "0086",
                    "email": "12123@qq.com"
                }
            }
        ]
    },
    "valueAddedBusiness": {
        "cargoValue": 10.0,
        "currencyCode": "RUB",
        "insurance": true,
        "pod": true
    },
    "settlementInfo": {
        "settlementPartyId": "4403721588833267713",
        "costCode": "0"
    },
    "attachments": [
        {
            "name": "运输下单测试用例-DEV.xlsx",
            "typeCode": "FLT_AFD",
            "url": "65241"
        }
    ]
}